mankey/__init__.py
mankey/charting_helper.py
mankey/custom_helpers.py
mankey/mankey_dataframe.py
mankey/stats_helpers.py
mankey_stats-0.1.1.dist-info/LICENSE
mankey_stats-0.1.1.dist-info/METADATA
mankey_stats-0.1.1.dist-info/WHEEL
mankey_stats-0.1.1.dist-info/top_level.txt
mankey_stats-0.1.1.dist-info/RECORD
