Metadata-Version: 2.1
Name: mankey-stats
Version: 0.1.1
Summary: Clean and transform data for ML binary classification with ease
Home-page: https://github.com/dBlueG/mankey_stats
Author: IE GROUP_A
Author-email: khalid.nass@student.ie.edu
License: UNKNOWN
Keywords: python,pandas,classification
Platform: UNKNOWN
Classifier: Programming Language :: Python :: 3
Classifier: License :: OSI Approved :: MIT License
Classifier: Development Status :: 3 - Alpha
Classifier: Intended Audience :: Education
Classifier: Programming Language :: Python :: 3
Classifier: Operating System :: MacOS :: MacOS X
Classifier: Operating System :: Microsoft :: Windows
Requires-Python: >=3.6
Requires-Dist: numpy
Requires-Dist: pandas
Requires-Dist: scikit-learn
Requires-Dist: scipy
Requires-Dist: plotly
Requires-Dist: matplotlib
Requires-Dist: seaborn
